pyasli/__init__.py
pyasli/browsers/__init__.py
pyasli/browsers/browser_session.py
pyasli/browsers/shared_browser.py
pyasli/bys.py
pyasli/conditions.py
pyasli/elements/__init__.py
pyasli/elements/elements.py
pyasli/elements/locators.py
pyasli/elements/searchable.py
pyasli/exceptions.py
pyasli/wait.py
pyasli-0.2.8.dist-info/LICENSE
pyasli-0.2.8.dist-info/METADATA
pyasli-0.2.8.dist-info/WHEEL
pyasli-0.2.8.dist-info/RECORD
