Metadata-Version: 2.1
Name: pyasli
Version: 0.2.8
Summary: (Python) Yet Another Selenium Instruments
License: MIT
Author: Anton Kachurin
Author-email: katchuring@gmail.com
Requires-Python: >=3.7,<4.0
Classifier: License :: OSI Approved :: MIT License
Classifier: Programming Language :: Python :: 3
Classifier: Programming Language :: Python :: 3.7
Classifier: Programming Language :: Python :: 3.8
Classifier: Programming Language :: Python :: 3.9
Classifier: Programming Language :: Python :: 3.10
Classifier: Programming Language :: Python :: 3.11
Requires-Dist: py (>=1.11.0,<2.0.0)
Requires-Dist: selenium (>=4.8,<5.0)
Requires-Dist: webdriver-manager (>=1.7,<2.0)
Requires-Dist: wrapt (>=1.11,<2.0)
